monosi/__init__.py
monosi/server/__init__.py
monosi/server/config.py
monosi/server/wsgi.py
monosi/tasks/__init__.py
monosi/tasks/server.py
monosi_server-0.0.1.dist-info/LICENSE
monosi_server-0.0.1.dist-info/METADATA
monosi_server-0.0.1.dist-info/WHEEL
monosi_server-0.0.1.dist-info/entry_points.txt
monosi_server-0.0.1.dist-info/top_level.txt
monosi_server-0.0.1.dist-info/RECORD
